[
  {"type": "video", "brand": "Sony (XAVC S)", "base": "ROOT", "pattern": "PRIVATE"},
  {"type": "video", "brand": "Sony (FX6)",    "base": "ROOT", "pattern": "XDROOT"},
  {"type": "video", "brand": "Canon",       "base": "DCIM", "pattern": "\\d{3}CANON"},
  {"type": "video", "brand": "Canon (Cinema RAW Light)", "base": "ROOT", "pattern": "CONTENTS"},
  {"type": "video", "brand": "Panasonic",   "base": "DCIM", "pattern": "\\d{3}_PANA"},
  {"type": "video", "brand": "Fujifilm",    "base": "DCIM", "pattern": "\\d{3}_FUJI"},
  {"type": "video", "brand": "Nikon",       "base": "DCIM", "pattern": "\\d{3}NIKON"},
  {"type": "video", "brand": "Olympus",     "base": "DCIM", "pattern": "\\d{3}OLYMP"},
  {"type": "video", "brand": "Leica",       "base": "DCIM", "pattern": "\\d{3}LEICA"},
  {"type": "video", "brand": "GoPro",       "base": "DCIM", "pattern": "\\d{3}GOPRO"},
  {"type": "video", "brand": "DJI",         "base": "DCIM", "pattern": "\\d{3}MEDIA"},
  {"type": "video", "brand": "DJI (Custom)", "base": "DCIM", "pattern": "DJI_\\d{3}_[A-Z0-9]+"},
  {"type": "photo", "brand": "DJI (Custom)", "base": "DCIM", "pattern": "DJI_\\d{3}_[A-Z0-9]+"},
  {"type": "video", "brand": "Insta360",    "base": "DCIM", "pattern": "Camera\\d{2}"},
  {"type": "video", "brand": "Blackmagic",  "base": "ROOT", "pattern": "\\d{4}_\\d{2}_\\d{2}_\\d{4}_C\\d{4}"},
  {"type": "video", "brand": "RED",         "base": "ROOT", "pattern": "[A-Z]\\d{3}_C\\d{3}_\\d{6}[A-Z]{2}\\.RDC"},
  {"type": "video", "brand": "ARRI",        "base": "ROOT", "pattern": "[A-Z]\\d{3}C\\d{3}_\\d{6}_[A-Z]\\d{3}"},
  {"type": "photo", "brand": "Sony",        "base": "DCIM", "pattern": "\\d{3}MSDCF"},
  {"type": "photo", "brand": "Sony",        "base": "DCIM", "pattern": "\\d{3}_\\d{6}|\\d+"},
  {"type": "photo", "brand": "Canon",       "base": "DCIM", "pattern": "\\d{3}CANON"},
  {"type": "photo", "brand": "Panasonic",   "base": "DCIM", "pattern": "\\d{3}_PANA"},
  {"type": "photo", "brand": "Fujifilm",    "base": "DCIM", "pattern": "\\d{3}_FUJI"},
  {"type": "photo", "brand": "Nikon",       "base": "DCIM", "pattern": "\\d{3}NIKON"},
  {"type": "photo", "brand": "Olympus",     "base": "DCIM", "pattern": "\\d{3}OLYMP"},
  {"type": "photo", "brand": "Leica",       "base": "DCIM", "pattern": "\\d{3}LEICA"},
  {"type": "photo", "brand": "GoPro",       "base": "DCIM", "pattern": "\\d{3}GOPRO"},
  {"type": "photo", "brand": "DJI",         "base": "DCIM", "pattern": "\\d{3}MEDIA"}
]
